maggot/__init__.py
maggot/__main__.py
maggot/config.py
maggot/containers.py
maggot/diffs.py
maggot/experiment.py
maggot/utils.py
maggot/scripts/__init__.py
maggot/scripts/config_diff.py
maggot/scripts/show_command.py
maggot/scripts/show_config.py
maggot/scripts/summarize.py
maggot-0.2.dist-info/LICENSE
maggot-0.2.dist-info/METADATA
maggot-0.2.dist-info/WHEEL
maggot-0.2.dist-info/entry_points.txt
maggot-0.2.dist-info/top_level.txt
maggot-0.2.dist-info/RECORD
