Metadata-Version: 2.1
Name: maggot
Version: 0.2
Summary: A lightweight python library for keeping track of numerical experiments
Home-page: UNKNOWN
Author: Dmytro Danevskyi
Author-email: d.danevskyi@gmail.com
License: UNKNOWN
Platform: UNKNOWN
Requires-Dist: maggot (==0.2)
Requires-Dist: numpy (==1.19.4)
Requires-Dist: pandas (==1.1.4)
Requires-Dist: pkg-resources (==0.0.0)
Requires-Dist: python-dateutil (==2.8.1)
Requires-Dist: pytz (==2020.4)
Requires-Dist: six (==1.15.0)
